aurigma/asset_processor/__init__.py
aurigma/asset_processor/api_client.py
aurigma/asset_processor/api_response.py
aurigma/asset_processor/configuration.py
aurigma/asset_processor/exceptions.py
aurigma/asset_processor/py.typed
aurigma/asset_processor/rest.py
aurigma/asset_processor/api/__init__.py
aurigma/asset_processor/api/build_info_api.py
aurigma/asset_processor/api/color_profile_processor_api.py
aurigma/asset_processor/api/data_schema_processor_api.py
aurigma/asset_processor/api/data_set_processor_api.py
aurigma/asset_processor/api/design_processor_api.py
aurigma/asset_processor/api/document_processor_api.py
aurigma/asset_processor/api/font_processor_api.py
aurigma/asset_processor/api/image_processor_api.py
aurigma/asset_processor/api/mockup_processor_api.py
aurigma/asset_processor/api/palette_processor_api.py
aurigma/asset_processor/api/private_design_processor_api.py
aurigma/asset_processor/api/private_image_processor_api.py
aurigma/asset_processor/api/private_mockup_processor_api.py
aurigma/asset_processor/models/__init__.py
aurigma/asset_processor/models/asset_relation.py
aurigma/asset_processor/models/blank_design_settings_model.py
aurigma/asset_processor/models/blank_design_source_settings_model.py
aurigma/asset_processor/models/build_info_model.py
aurigma/asset_processor/models/color_profile_class.py
aurigma/asset_processor/models/color_profile_dto.py
aurigma/asset_processor/models/color_profile_metadata.py
aurigma/asset_processor/models/color_space.py
aurigma/asset_processor/models/conflict_dto.py
aurigma/asset_processor/models/conflict_type.py
aurigma/asset_processor/models/copy_design_from_public_design_model.py
aurigma/asset_processor/models/copy_design_from_public_resource_model.py
aurigma/asset_processor/models/create_blank_design_model.py
aurigma/asset_processor/models/create_blank_toggle_set_model.py
aurigma/asset_processor/models/create_design_from_mockup_model.py
aurigma/asset_processor/models/data_schema_dto.py
aurigma_asset_processor_api_client-1.0.0.dist-info/METADATA
aurigma_asset_processor_api_client-1.0.0.dist-info/WHEEL
aurigma_asset_processor_api_client-1.0.0.dist-info/top_level.txt
aurigma_asset_processor_api_client-1.0.0.dist-info/RECORD
