Metadata-Version: 2.4
Name: aurigma-asset-processor-api-client
Version: 1.0.0
Summary: Aurigma Asset Processor API client
Requires-Python: >=3.9
Requires-Dist: python-dateutil>=2.8.2
Requires-Dist: httpx>=0.28.1
Requires-Dist: pydantic<3,>=2
Requires-Dist: typing-extensions>=4.7.1; python_version < "3.11"
